<?xml version="1.0" encoding="UTF-8"?>
<objects serializationModel="Studio.02.02.00">
	<object class="AudioFile" id="{316f52c7-b0b5-4b33-b09a-f5d917ea3386}">
		<property name="assetPath">
			<value>footsteps/rt/grass/rt_walk_grass-005.wav</value>
		</property>
		<property name="frequencyInKHz">
			<value>48</value>
		</property>
		<property name="channelCount">
			<value>2</value>
		</property>
		<property name="length">
			<value>1.5375624999999999</value>
		</property>
		<relationship name="masterAssetFolder">
			<destination>{6ab7ca78-a7cc-4484-8759-72c2162791e9}</destination>
		</relationship>
	</object>
</objects>
