<?xml version="1.0" encoding="UTF-8"?>
<objects serializationModel="Studio.02.02.00">
	<object class="AudioFile" id="{7c0bd16a-ec59-4767-9957-8bf3a4cbd5fe}">
		<property name="assetPath">
			<value>scifi/Impact - Hydroplane.wav</value>
		</property>
		<property name="frequencyInKHz">
			<value>96</value>
		</property>
		<property name="channelCount">
			<value>2</value>
		</property>
		<property name="length">
			<value>4.5958125000000001</value>
		</property>
		<relationship name="masterAssetFolder">
			<destination>{6ab7ca78-a7cc-4484-8759-72c2162791e9}</destination>
		</relationship>
	</object>
</objects>
